Workbook
Name Slicer_Genre: #N/A

Sheet Dashboard
B2: Library Sales & Management Performance

Sheet Genre Chart
A3: Row Labels | B3: Sum of Total Profit
A4: Fantasy | B4: 816.2
A5: Sci-Fi | B5: 634.4
A6: Grand Total | B6: 1450.6

Sheet Manager Chart
A3: Row Labels | B3: Sum of Total Profit
A4: James | B4: 443.8
A5: Mike | B5: 590.6
A6: Sarah | B6: 416.2
A7: Grand Total | B7: 1450.6

Sheet Efficiency Chart
A3: Row Labels | B3: Sum of Profit per Staff
A4: London | B4: 36.983333
A5: Portsmouth | B5: 83.24
A6: Southampton | B6: 196.86667
A7: Grand Total | B7: 317.09

Sheet Sales
A1: Order_ID | B1: Date | C1: Book_ID | D1: Store_Location | E1: Units_Sold | F1: Unit Price | G1: Cost | H1: Total Revenue | I1: Total Cost | J1: Total Profit
A2: ORD-101 | B2: 46068 | C2: BK001 | D2: Portsmouth | E2: 2 | F2: =_xlfn.XLOOKUP(C2, Products!$A$2:$A$11, Products!$G$2:$G$11) -> 22.5 | G2: =_xlfn.XLOOKUP(C2, Products!$A$2:$A$11, Products!$F$2:$F$11) -> 13.5 | H2: =E2*F2 -> 45 | I2: =E2*G2 -> 27 | J2: =(F2 - G2) * E2 -> 18
A3: ORD-102 | B3: 46068 | C3: BK003 | D3: London | E3: 5 | F3: =_xlfn.XLOOKUP(C3, Products!$A$2:$A$11, Products!$G$2:$G$11) -> 15 | G3: =_xlfn.XLOOKUP(C3, Products!$A$2:$A$11, Products!$F$2:$F$11) -> 9 | H3: =E3*F3 -> 75 | I3: =E3*G3 -> 45 | J3: =(F3 - G3) * E3 -> 30
A4: ORD-103 | B4: 46068 | C4: BK006 | D4: Portsmouth | E4: 2 | F4: =_xlfn.XLOOKUP(C4, Products!$A$2:$A$11, Products!$G$2:$G$11) -> 14.5 | G4: =_xlfn.XLOOKUP(C4, Products!$A$2:$A$11, Products!$F$2:$F$11) -> 8.7 | H4: =E4*F4 -> 29 | I4: =E4*G4 -> 17.4 | J4: =(F4 - G4) * E4 -> 11.6
A5: ORD-104 | B5: 46069 | C5: BK007 | D5: Southampton | E5: 3 | F5: =_xlfn.XLOOKUP(C5, Products!$A$2:$A$11, Products!$G$2:$G$11) -> 20 | G5: =_xlfn.XLOOKUP(C5, Products!$A$2:$A$11, Products!$F$2:$F$11) -> 12 | H5: =E5*F5 -> 60 | I5: =E5*G5 -> 36 | J5: =(F5 - G5) * E5 -> 24
A6: ORD-105 | B6: 46070 | C6: BK005 | D6: London | E6: 10 | F6: =_xlfn.XLOOKUP(C6, Products!$A$2:$A$11, Products!$G$2:$G$11) -> 10 | G6: =_xlfn.XLOOKUP(C6, Products!$A$2:$A$11, Products!$F$2:$F$11) -> 6 | H6: =E6*F6 -> 100 | I6: =E6*G6 -> 60 | J6: =(F6 - G6) * E6 -> 40
A7: ORD-106 | B7: 46070 | C7: BK004 | D7: Portsmouth | E7: 2 | F7: =_xlfn.XLOOKUP(C7, Products!$A$2:$A$11, Products!$G$2:$G$11) -> 12 | G7: =_xlfn.XLOOKUP(C7, Products!$A$2:$A$11, Products!$F$2:$F$11) -> 7.2 | H7: =E7*F7 -> 24 | I7: =E7*G7 -> 14.4 | J7: =(F7 - G7) * E7 -> 9.6
A8: ORD-107 | B8: 46071 | C8: BK002 | D8: London | E8: 1 | F8: =_xlfn.XLOOKUP(C8, Products!$A$2:$A$11, Products!$G$2:$G$11) -> 18 | G8: =_xlfn.XLOOKUP(C8, Products!$A$2:$A$11, Products!$F$2:$F$11) -> 10.8 | H8: =E8*F8 -> 18 | I8: =E8*G8 -> 10.8 | J8: =(F8 - G8) * E8 -> 7.2
A9: ORD-108 | B9: 46071 | C9: BK008 | D9: Portsmouth | E9: 4 | F9: =_xlfn.XLOOKUP(C9, Products!$A$2:$A$11, Products!$G$2:$G$11) -> 25 | G9: =_xlfn.XLOOKUP(C9, Products!$A$2:$A$11, Products!$F$2:$F$11) -> 15 | H9: =E9*F9 -> 100 | I9: =E9*G9 -> 60 | J9: =(F9 - G9) * E9 -> 40
A10: ORD-109 | B10: 46072 | C10: BK009 | D10: Southampton | E10: 2 | F10: =_xlfn.XLOOKUP(C10, Products!$A$2:$A$11, Products!$G$2:$G$11) -> 11 | G10: =_xlfn.XLOOKUP(C10, Products!$A$2:$A$11, Products!$F$2:$F$11) -> 6.6 | H10: =E10*F10 -> 22 | I10: =E10*G10 -> 13.2 | J10: =(F10 - G10) * E10 -> 8.8
A11: ORD-110 | B11: 46072 | C11: BK010 | D11: London | E11: 6 | F11: =_xlfn.XLOOKUP(C11, Products!$A$2:$A$11, Products!$G$2:$G$11) -> 16 | G11: =_xlfn.XLOOKUP(C11, Products!$A$2:$A$11, Products!$F$2:$F$11) -> 9.6 | H11: =E11*F11 -> 96 | I11: =E11*G11 -> 57.6 | J11: =(F11 - G11) * E11 -> 38.4
A12: ORD-111 | B12: 46073 | C12: BK001 | D12: Portsmouth | E12: 1 | F12: =_xlfn.XLOOKUP(C12, Products!$A$2:$A$11, Products!$G$2:$G$11) -> 22.5 | G12: =_xlfn.XLOOKUP(C12, Products!$A$2:$A$11, Products!$F$2:$F$11) -> 13.5 | H12: =E12*F12 -> 22.5 | I12: =E12*G12 -> 13.5 | J12: =(F12 - G12) * E12 -> 9
A13: ORD-112 | B13: 46073 | C13: BK002 | D13: Southampton | E13: 8 | F13: =_xlfn.XLOOKUP(C13, Products!$A$2:$A$11, Products!$G$2:$G$11) -> 18 | G13: =_xlfn.XLOOKUP(C13, Products!$A$2:$A$11, Products!$F$2:$F$11) -> 10.8 | H13: =E13*F13 -> 144 | I13: =E13*G13 -> 86.4 | J13: =(F13 - G13) * E13 -> 57.6
... A51: ORD-150 | B51: 46092 | C51: BK001 | D51: Southampton | E51: 6 | F51: =_xlfn.XLOOKUP(C51, Products!$A$2:$A$11, Products!$G$2:$G$11) -> 22.5 | G51: =_xlfn.XLOOKUP(C51, Products!$A$2:$A$11, Products!$F$2:$F$11) -> 13.5 | H51: =E51*F51 -> 135 | I51: =E51*G51 -> 81 | J51: =(F51 - G51) * E51 -> 54

Sheet Products
A1: Book_ID | B1: Title | C1: Author | D1: Genre | E1: Stock (Units) | F1: Cost | G1: Price
A2: BK001 | B2: The Way of Kings | C2: Sanderson | D2: Fantasy | E2: 15 | F2: =Tab_Products[[#This Row],[Price]]*0.6 -> 13.5 | G2: 22.5
A3: BK002 | B3: Leviathan Wakes | C3: Corey | D3: Sci-Fi | E3: 8 | F3: =Tab_Products[[#This Row],[Price]]*0.6 -> 10.8 | G3: 18
A4: BK003 | B4: Red Sister | C4: Lawrence | D4: Fantasy | E4: 0 | F4: =Tab_Products[[#This Row],[Price]]*0.6 -> 9 | G4: 15
A5: BK004 | B5: Neuromancer | C5: Gibson | D5: Sci-Fi | E5: 12 | F5: =Tab_Products[[#This Row],[Price]]*0.6 -> 7.2 | G5: 12
A6: BK005 | B6: Foundation | C6: Asimov | D6: Sci-Fi | E6: 5 | F6: =Tab_Products[[#This Row],[Price]]*0.6 -> 6 | G6: 10
A7: BK006 | B7: The Blade Itself | C7: Abercrombie | D7: Fantasy | E7: 20 | F7: =Tab_Products[[#This Row],[Price]]*0.6 -> 8.7 | G7: 14.5
A8: BK007 | B8: Project Hail Mary | C8: Weir | D8: Sci-Fi | E8: 0 | F8: =Tab_Products[[#This Row],[Price]]*0.6 -> 12 | G8: 20
A9: BK008 | B9: The Name of the Wind | C9: Rothfuss | D9: Fantasy | E9: 4 | F9: =Tab_Products[[#This Row],[Price]]*0.6 -> 15 | G9: 25
A10: BK009 | B10: Dune | C10: Herbert | D10: Sci-Fi | E10: 30 | F10: =Tab_Products[[#This Row],[Price]]*0.6 -> 6.6 | G10: 11
A11: BK010 | B11: The Lies of Locke Lamora | C11: Lynch | D11: Fantasy | E11: 0 | F11: =Tab_Products[[#This Row],[Price]]*0.6 -> 9.6 | G11: 16

Sheet Managers
A1: Store_Location | B1: Manager | C1: Staff_Count
A2: Portsmouth | B2: Sarah | C2: 5
A3: London | B3: James | C3: 12
A4: Southampton | B4: Mike | C4: 3
A15: Store | B15: Total Profit | C15: Staff Count | D15: Profit per Staff
A16: Southampton | B16: =GETPIVOTDATA("[Measures].[Sum of Total Profit]",'Manager Chart'!$A$3,"[Tab_Managers].[Manager]","[Tab_Managers].[Manager].&[Mike]") -> 590.6 | C16: 3 | D16: =B16/C16 -> 196.86667
A17: Portsmouth | B17: =GETPIVOTDATA("[Measures].[Sum of Total Profit]",'Manager Chart'!$A$3,"[Tab_Managers].[Manager]","[Tab_Managers].[Manager].&[Sarah]") -> 416.2 | C17: 5 | D17: =B17/C17 -> 83.24
A18: London | B18: =GETPIVOTDATA("[Measures].[Sum of Total Profit]",'Manager Chart'!$A$3,"[Tab_Managers].[Manager]","[Tab_Managers].[Manager].&[James]") -> 443.8 | C18: 12 | D18: =B18/C18 -> 36.983333
